{
	"info": {
		"_postman_id": "47b45f2f-3cfd-4838-a864-6d4dd54a8746",
		"name": "Codigo HTTP Watchlist",
		"schema": "https://schema.getpostman.com/json/collection/v2.1.0/collection.json"
	},
	"item": [
		{
			"name": "Obtener Todas Las Watchlist",
			"request": {
				"method": "GET",
				"header": [],
				"url": {
					"raw": "localhost:8080/api/v1/watchlist",
					"host": [
						"localhost"
					],
					"port": "8080",
					"path": [
						"api",
						"v1",
						"watchlist"
					]
				}
			},
			"response": []
		},
		{
			"name": "Obtener Wacthlist por id",
			"request": {
				"method": "GET",
				"header": [],
				"url": {
					"raw": "localhost:8080/api/v1/watchlist/1",
					"host": [
						"localhost"
					],
					"port": "8080",
					"path": [
						"api",
						"v1",
						"watchlist",
						"1"
					]
				}
			},
			"response": []
		},
		{
			"name": "Agregar Watchlist",
			"request": {
				"method": "POST",
				"header": [],
				"body": {
					"mode": "raw",
					"raw": "{\r\n\"pelicula\":{\r\n    \"id_pelicula\": 1,\r\n    \"titulo_pelicula\": \"Rapidos y furiosos 6\",\r\n    \"autor\": {\r\n        \"id_autor\": 1,\r\n        \"nombre_autor\": \"Juan\",\r\n        \"apellido_autor\": \"Lobos\",\r\n        \"edad_autor\": 35\r\n        },\r\n    \"descripcion\": \"Algo de pelicula\",\r\n    \"genero_pelicula\": \"Accion\",\r\n    \"duracion\": \"2 Hrs y 12 Minutos\",\r\n    \"fecha_estreno_pelicula\": \"20-05-2012\",\r\n    \"productora\": {\r\n        \"id_productora\": 1,\r\n        \"nombre_productora\": \"Marvel\"\r\n        }\r\n    },\r\n    \"usuario\":{\r\n        \"id_usuario\": 1,\r\n        \"nombre_usuario\": \"Gustavo\",\r\n        \"apellido_usuario\": \"Saavedra\",\r\n        \"email_usuario\": \"GSaa@gmail.com\",\r\n        \"contraseña_usuario\": \"123456\",\r\n        \"fecha_creacion_cuenta_usuario\": \"30-04-2024\",\r\n        \"edad_usuario\": 16\r\n    },\r\n\"tamano_watchlist\": 500\r\n}\r\n",
					"options": {
						"raw": {
							"language": "json"
						}
					}
				},
				"url": {
					"raw": "localhost:8080/api/v1/watchlist",
					"host": [
						"localhost"
					],
					"port": "8080",
					"path": [
						"api",
						"v1",
						"watchlist"
					]
				}
			},
			"response": []
		},
		{
			"name": "Actualizar Watchlist",
			"request": {
				"method": "PUT",
				"header": [],
				"body": {
					"mode": "raw",
					"raw": "{\r\n    \"id_watchlist\": 1,\r\n    \"pelicula\": {\r\n        \"id_pelicula\": 2,\r\n        \"titulo_pelicula\": \"Rapidos y furiosos 6\",\r\n        \"autor\": {\r\n            \"id_autor\": 1,\r\n            \"nombre_autor\": \"Juan\",\r\n            \"apellido_autor\": \"Lobos\",\r\n            \"edad_autor\": 35\r\n        },\r\n        \"descripcion\": \"Algo de pelicula\",\r\n        \"genero_pelicula\": \"Accion\",\r\n        \"duracion\": \"2 Hrs y 12 Minutos\",\r\n        \"fecha_estreno_pelicula\": \"20-05-2012\",\r\n        \"productora\": {\r\n            \"id_productora\": 1,\r\n            \"nombre_productora\": \"Marvel\"\r\n        }\r\n    },\r\n    \"usuario\": {\r\n        \"id_usuario\": 1,\r\n        \"nombre_usuario\": \"Gustavo\",\r\n        \"apellido_usuario\": \"Saavedra\",\r\n        \"email_usuario\": \"GSaa@gmail.com\",\r\n        \"contraseña_usuario\": \"123456\",\r\n        \"fecha_creacion_cuenta_usuario\": \"30-04-2024\",\r\n        \"edad_usuario\": 16\r\n    },\r\n    \"tamano_watchlist\": 1000\r\n}",
					"options": {
						"raw": {
							"language": "json"
						}
					}
				},
				"url": {
					"raw": "localhost:8080/api/v1/watchlist/1",
					"host": [
						"localhost"
					],
					"port": "8080",
					"path": [
						"api",
						"v1",
						"watchlist",
						"1"
					]
				}
			},
			"response": []
		},
		{
			"name": "Borrar Watchlist",
			"request": {
				"method": "DELETE",
				"header": [],
				"url": {
					"raw": "localhost:8080/api/v1/watchlist/1",
					"host": [
						"localhost"
					],
					"port": "8080",
					"path": [
						"api",
						"v1",
						"watchlist",
						"1"
					]
				}
			},
			"response": []
		}
	]
}